geo_explorer/__init__.py
geo_explorer/assets/chroma.min.js
geo_explorer/assets/on_each_feature.js
geo_explorer/assets/stylesheet.css
geo_explorer/file_browser.py
geo_explorer/fs.py
geo_explorer/geo_explorer.py
geo_explorer/nc.py
geo_explorer/utils.py
geo_explorer-0.9.10.dist-info/LICENSE
geo_explorer-0.9.10.dist-info/LICENSE.md
geo_explorer-0.9.10.dist-info/METADATA
geo_explorer-0.9.10.dist-info/WHEEL
geo_explorer-0.9.10.dist-info/RECORD
