Metadata-Version: 2.3
Name: geo-explorer
Version: 0.9.10
Summary: Explore geodata interactively.
License: MIT
Author: Morten Letnes
Author-email: morten.letnes@ssb.no
Requires-Python: >=3.11,<4
Classifier: Development Status :: 5 - Production/Stable
Classifier: License :: OSI Approved :: MIT License
Classifier: Programming Language :: Python :: 3
Classifier: Programming Language :: Python :: 3.11
Classifier: Programming Language :: Python :: 3.12
Classifier: Programming Language :: Python :: 3.13
Classifier: Topic :: Scientific/Engineering :: GIS
Requires-Dist: dash (>=2.0.0)
Requires-Dist: dash-bootstrap-components (>=1.7.1)
Requires-Dist: dash-leaflet (>=1.1.3)
Requires-Dist: fsspec (>=2024.10.1)
Requires-Dist: geopandas (>=0.14.0)
Requires-Dist: jenkspy (>=0.3.2)
Requires-Dist: matplotlib (>=3.7.0)
Requires-Dist: msgspec (>=0.19.0)
Requires-Dist: numpy (>=1.26.4)
Requires-Dist: pandas (>=2.2.1)
Requires-Dist: polars (>=1.32.0)
Requires-Dist: pyarrow (>=20.0.0)
Requires-Dist: pyproj (>=3.6.1)
Requires-Dist: rtree (>=1.0.1)
Requires-Dist: shapely (>=2.0.1)
Requires-Dist: ssb-sgis (>=1.3.1)
Requires-Dist: typing-extensions (>=4.11.0)
Requires-Dist: tzlocal (>=5.3.1)
Project-URL: Changelog, https://github.com/statisticsnorway/geo-explorer/releases
Project-URL: Documentation, https://statisticsnorway.github.io/geo-explorer
Project-URL: Homepage, https://github.com/statisticsnorway/geo-explorer
Project-URL: Repository, https://github.com/statisticsnorway/geo-explorer
